sctefu/__init__.py
sctefu/base.py
sctefu/bitn.py
sctefu/commands.py
sctefu/crc.py
sctefu/cue.py
sctefu/descriptors.py
sctefu/hls.py
sctefu/iframes.py
sctefu/new_reader.py
sctefu/packetdata.py
sctefu/section.py
sctefu/segment.py
sctefu/segmentation.py
sctefu/sixfix.py
sctefu/spare.py
sctefu/stream.py
sctefu/streamtypes.py
sctefu/sxp.py
sctefu/upids.py
sctefu/version.py
sctefu/x2c.py
sctefu/xml.py
sctefu-3.0.5.data/scripts/sctefu
sctefu-3.0.5.dist-info/LICENSE
sctefu-3.0.5.dist-info/METADATA
sctefu-3.0.5.dist-info/WHEEL
sctefu-3.0.5.dist-info/top_level.txt
sctefu-3.0.5.dist-info/RECORD
