Metadata-Version: 2.1
Name: sctefu
Version: 3.0.5
Summary: Fumatic SCTE-35 Encoder/ Decoder for MPEGTS, HLS , DASH and everything else... 
Home-page: https://github.com/superkabuki/scte35
Author: Adrian of Doom
Author-email: spam@iodisco.com
License: UNKNOWN
Platform: UNKNOWN
Classifier: License :: OSI Approved :: Sleepycat License
Classifier: Environment :: Console
Classifier: Operating System :: OS Independent
Classifier: Operating System :: POSIX :: BSD :: OpenBSD
Classifier: Operating System :: POSIX :: BSD :: NetBSD
Classifier: Operating System :: POSIX :: Linux
Classifier: Topic :: Multimedia :: Video
Classifier: Programming Language :: Python :: 3.6
Classifier: Programming Language :: Python :: Implementation :: PyPy
Classifier: Programming Language :: Python :: Implementation :: CPython
Requires-Python: >=3.8
Requires-Dist: m3ufu (>=0.0.89)
Requires-Dist: sideways (>=0.0.23)
Requires-Dist: pyaes
